one4all_iop_models/__init__.py
one4all_iop_models/ros_models/__init__.py
one4all_iop_models/ros_models/robot.py
one4all_iop_models-0.1.23.dist-info/METADATA
one4all_iop_models-0.1.23.dist-info/WHEEL
one4all_iop_models-0.1.23.dist-info/RECORD
